PyScaffolder.cpython-311-x86_64-linux-gnu.so
liblua-5.3.5.a
pyscaffolder.libs/libgomp-870cb1d0.so.1.0.0
pyscaffolder-1.5.3.dist-info/METADATA
pyscaffolder-1.5.3.dist-info/WHEEL
pyscaffolder-1.5.3.dist-info/top_level.txt
pyscaffolder-1.5.3.dist-info/RECORD
pyscaffolder-1.5.3.dist-info/licenses/LICENSE
