Metadata-Version: 2.1
Name: PyScaffolder
Version: 1.5.3
Summary: Generate 3D mesh from implicit surface and an input mesh
Home-page: https://github.com/nodtem66/Scaffolder
Author: Jirawat Iamsamang
Author-email: nodtem66@gmail.com
License: MIT
Project-URL: Bug Tracker, https://github.com/nodtem66/Scaffolder/issues
Classifier: Programming Language :: Python :: 3
Classifier: Programming Language :: Python :: Implementation :: CPython
Classifier: Topic :: Scientific/Engineering
Classifier: Topic :: Software Development :: Libraries
Requires-Python: >=3.7
License-File: LICENSE
